_prismataengine.cpython-38-x86_64-linux-gnu.so
prismataengine.cpython-38-x86_64-linux-gnu.so
prismataengine/__init__.py
prismataengine/cardLibrary.jso
prismataengine-2.0.6.dist-info/LICENSE
prismataengine-2.0.6.dist-info/METADATA
prismataengine-2.0.6.dist-info/WHEEL
prismataengine-2.0.6.dist-info/top_level.txt
prismataengine-2.0.6.dist-info/RECORD
